gtrans.py
mygoogletrans-1.0.0.dist-info/METADATA
mygoogletrans-1.0.0.dist-info/WHEEL
mygoogletrans-1.0.0.dist-info/RECORD
